cal/__init__.py
akcalculator-0.1.dist-info/LICENCE.txt
akcalculator-0.1.dist-info/METADATA
akcalculator-0.1.dist-info/WHEEL
akcalculator-0.1.dist-info/top_level.txt
akcalculator-0.1.dist-info/RECORD
