Metadata-Version: 2.1
Name: akcalculator
Version: 0.1
Summary: A simple-calculator is a python package that performs arithmetic operations on numbers.
Home-page: UNKNOWN
Author: Amogh Kawle
Author-email: rohitkawle810@gmail.com
License: UNKNOWN
Platform: UNKNOWN
Classifier: Programming Language :: Python :: 3
Classifier: License :: OSI Approved :: MIT License
Classifier: Operating System :: OS Independent
